{
    "products": [
        {
            "id": 1,
            "title": "Patateuse",
            "description": "La patateuse du siècle.",
            "price": 50000,
            "pictures": [
                "https://restaudepot.fr/1529-large_default/eplucheuse-patateuse-8kg.jpg",
                "https://restaudepot.fr/1532-large_default/eplucheuse-patateuse-8kg.jpg"
            ],
            "type": "bakery",
            "secondHand": true
        },
        {
            "id": 2,
            "title": "Pétrin",
            "description": "Le pétrin du siècle.",
            "price": 100000,
            "pictures": [
                "http://www.lafoiredupro.com/petrin-spirale-boulangerie-bongard-1211.jpg",
                "https://www.caplainmachines.com/wp-content/uploads/2021/04/PETRIN-PE60MC-TR-1-768x768.jpg"
            ],
            "type": "bakery",
            "secondHand": false
        },
        {
            "id": 3,
            "title": "Lave-verres",
            "description": "Le lave-verres du siècle.",
            "price": 80000,
            "pictures": [
                "https://www.restoconcept.com/lave-verres-400x400-combisteel-1197321.jpg",
                "https://www.equipementpro.fr/59734-thickbox_default/lave-verres-gastro-m-gw35-230v-equipementpro.jpg"
            ],
            "type": "catering",
            "secondHand": true
        },
        {
            "id": 4,
            "title": "Plonge",
            "description": "La plonge du siècle.",
            "price": 60000,
            "pictures": [
                "https://kvt-occasions.fr/wp-content/uploads/2015/03/928-plonge-inox-avec-emp-lave-vaisselle-1-1.jpg",
                "https://tse1.mm.bing.net/th?id=OIP.c-FS149B0GiCHcVmeExSqwHaFj&pid=Api"
            ],
            "type": "catering",
            "secondHand": false
        },
        {
            "id": 5,
            "title": "Trancheuse à pain",
            "description": "La trancheuse à pain du siècle.",
            "price": 30000,
            "pictures": [
                "https://kvt-occasions.fr/wp-content/uploads/2015/12/1217-trancheuse-picomatic-2.jpg",
                "https://kvt-occasions.fr/wp-content/uploads/2015/12/1217-trancheuse-picomatic-4.jpg"
            ],
            "type": "miscellaneous",
            "secondHand": true
        },
        {
            "id": 6,
            "title": "Plaques",
            "description": "Les plaques du siècle.",
            "price": 2500,
            "pictures": [
                "https://kvt-occasions.fr/wp-content/uploads/2017/01/plaques-magasin1-1024x1024.png",
                "https://kvt-occasions.fr/wp-content/uploads/2017/01/plaque-patissiere-tole-noire-21-510x510.png"
            ],
            "type": "miscellaneous",
            "secondHand": false
        }
    ]
}
